youngjin_langchain_tools/__init__.py
youngjin_langchain_tools/handlers/__init__.py
youngjin_langchain_tools/handlers/streamlit_langgraph_handler.py
youngjin_langchain_tools/utils/__init__.py
youngjin_langchain_tools/utils/config.py
youngjin_langchain_tools-0.1.1.dist-info/METADATA
youngjin_langchain_tools-0.1.1.dist-info/WHEEL
youngjin_langchain_tools-0.1.1.dist-info/licenses/LICENSE
youngjin_langchain_tools-0.1.1.dist-info/RECORD
