Metadata-Version: 2.4
Name: youngjin-langchain-tools
Version: 0.1.1
Summary: LangGraph utilities for Streamlit - StreamlitLanggraphHandler and more
Project-URL: Homepage, https://github.com/yourusername/youngjin-langchain-tools
Project-URL: Documentation, https://github.com/yourusername/youngjin-langchain-tools#readme
Project-URL: Repository, https://github.com/yourusername/youngjin-langchain-tools.git
Project-URL: Issues, https://github.com/yourusername/youngjin-langchain-tools/issues
Project-URL: Changelog, https://github.com/yourusername/youngjin-langchain-tools/releases
Author-email: YoungJin <your-email@example.com>
Maintainer-email: YoungJin <your-email@example.com>
License: Apache-2.0
License-File: LICENSE
Keywords: agents,ai,callback,handler,langchain,langgraph,llm,streamlit
Classifier: Development Status :: 3 - Alpha
Classifier: Intended Audience :: Developers
Classifier: License :: OSI Approved :: Apache Software License
Classifier: Programming Language :: Python :: 3
Classifier: Programming Language :: Python :: 3.12
Classifier: Programming Language :: Python :: 3.13
Classifier: Programming Language :: Python :: 3.14
Classifier: Topic :: Scientific/Engineering :: Artificial Intelligence
Classifier: Topic :: Software Development :: Libraries :: Python Modules
Requires-Python: >=3.12
Requires-Dist: langchain-core<1.2.7,>=1.0.0
Requires-Dist: langchain<1.2.7,>=1.0.0
Requires-Dist: pydantic>=2.0.0
Provides-Extra: dev
Requires-Dist: mypy>=1.10.0; extra == 'dev'
Requires-Dist: pytest-cov>=4.0.0; extra == 'dev'
Requires-Dist: pytest>=8.0.0; extra == 'dev'
Requires-Dist: ruff>=0.4.0; extra == 'dev'
Requires-Dist: streamlit>=1.30.0; extra == 'dev'
Provides-Extra: streamlit
Requires-Dist: streamlit>=1.30.0; extra == 'streamlit'
